docs2markdown/__init__.py
docs2markdown/__main__.py
docs2markdown/cli.py
docs2markdown/convert.py
docs2markdown/html.py
docs2markdown/markdown.py
docs2markdown/py.typed
docs2markdown-0.4.1.dist-info/WHEEL
docs2markdown-0.4.1.dist-info/entry_points.txt
docs2markdown-0.4.1.dist-info/METADATA
docs2markdown-0.4.1.dist-info/RECORD
