Metadata-Version: 2.3
Name: docs2markdown
Version: 0.4.1
Summary: Convert HTML documentation to Markdown
Author: Josh Thomas
Author-email: Josh Thomas <josh@joshthomas.dev>
License: MIT License
Classifier: Development Status :: 4 - Beta
Classifier: License :: OSI Approved :: MIT License
Classifier: Operating System :: OS Independent
Classifier: Programming Language :: Python
Classifier: Programming Language :: Python :: 3
Classifier: Programming Language :: Python :: 3 :: Only
Classifier: Programming Language :: Python :: 3.10
Classifier: Programming Language :: Python :: 3.11
Classifier: Programming Language :: Python :: 3.12
Classifier: Programming Language :: Python :: 3.13
Classifier: Programming Language :: Python :: 3.14
Classifier: Programming Language :: Python :: Free Threading
Classifier: Programming Language :: Python :: Implementation :: CPython
Requires-Dist: beautifulsoup4[lxml]>=4.14.2
Requires-Dist: markdownify>=1.2.0
Requires-Dist: pydantic>=2.12.1
Requires-Dist: rich>=14.2.0
Requires-Dist: typer>=0.19.2
Requires-Python: >=3.10
Project-URL: Documentation, https://github.com/joshuadavidthomas/docs2markdown#README
Project-URL: Issues, https://github.com/joshuadavidthomas/docs2markdown/issues
Project-URL: Source, https://github.com/joshuadavidthomas/docs2markdown
